{
  "node": {
    "78a14ad9c1d369891b5a46440c679e86f60754b5": {
      "workers": {
        "app/admin/events/new/page": "(rsc)/./node_modules/next/dist/build/webpack/loaders/next-flight-action-entry-loader.js?actions=%5B%5B%22%2FUsers%2Fisq%2FDocuments%2FEvent%20Registration%20App%2Fapp%2Fadmin%2Fevents%2Fnew%2Fpage.tsx%22%2C%5B%22%24%24ACTION_0%22%5D%5D%5D&__client_imported__=!"
      },
      "layer": {
        "app/admin/events/new/page": "rsc"
      }
    },
    "9fccc8bcd793019caefca77806dca7ae3c28e26b": {
      "workers": {
        "app/admin/events/[id]/page": "(rsc)/./node_modules/next/dist/build/webpack/loaders/next-flight-action-entry-loader.js?actions=%5B%5B%22%2FUsers%2Fisq%2FDocuments%2FEvent%20Registration%20App%2Fapp%2Fadmin%2Fevents%2F%5Bid%5D%2Fpage.tsx%22%2C%5B%22%24%24ACTION_0%22%5D%5D%5D&__client_imported__=!"
      },
      "layer": {
        "app/admin/events/[id]/page": "rsc"
      }
    }
  },
  "edge": {},
  "encryptionKey": "jsckyPnIRgysrMAePZjfMXVVJa5aueuN5KnTW96bUxI="
}